<?xml version="1.0" encoding="UTF-8"?>
<!DOCTYPE mapper PUBLIC "-//mybatis.org//DTD Mapper 3.0//EN" "http://mybatis.org/dtd/mybatis-3-mapper.dtd">
<mapper namespace="cn.ch1tanda.event.mapper.UserMapper">
  <resultMap id="BaseResultMap" type="cn.ch1tanda.event.model.User">
    <!--
      WARNING - @mbg.generated
      This element is automatically generated by MyBatis Generator, do not modify.
      This element was generated on Wed Jul 13 23:55:47 GMT+08:00 2022.
    -->
    <id column="id" jdbcType="INTEGER" property="id" />
    <result column="gmt_created" jdbcType="TIMESTAMP" property="gmtCreated" />
    <result column="gmt_modified" jdbcType="TIMESTAMP" property="gmtModified" />
    <result column="gmt_deleted" jdbcType="TIMESTAMP" property="gmtDeleted" />
    <result column="remark" jdbcType="VARCHAR" property="remark" />
    <result column="username" jdbcType="VARCHAR" property="username" />
    <result column="password" jdbcType="VARCHAR" property="password" />
    <result column="enabled" jdbcType="BIT" property="enabled" />
    <result column="email" jdbcType="VARCHAR" property="email" />
  </resultMap>
  <delete id="deleteByPrimaryKey" parameterType="java.lang.Integer">
    <!--
      WARNING - @mbg.generated
      This element is automatically generated by MyBatis Generator, do not modify.
      This element was generated on Wed Jul 13 23:55:47 GMT+08:00 2022.
    -->
    delete from user
    where id = #{id,jdbcType=INTEGER}
  </delete>
  <insert id="insert" parameterType="cn.ch1tanda.event.model.User">
    <!--
      WARNING - @mbg.generated
      This element is automatically generated by MyBatis Generator, do not modify.
      This element was generated on Wed Jul 13 23:55:47 GMT+08:00 2022.
    -->
    insert into user (id, gmt_created, gmt_modified, 
      gmt_deleted, remark, username, 
      password, enabled, email)
    values (#{id,jdbcType=INTEGER}, #{gmtCreated,jdbcType=TIMESTAMP}, #{gmtModified,jdbcType=TIMESTAMP}, 
      #{gmtDeleted,jdbcType=TIMESTAMP}, #{remark,jdbcType=VARCHAR}, #{username,jdbcType=VARCHAR}, 
      #{password,jdbcType=VARCHAR}, #{enabled,jdbcType=BIT}, #{email})
  </insert>
  <update id="updateByPrimaryKey" parameterType="cn.ch1tanda.event.model.User">
    <!--
      WARNING - @mbg.generated
      This element is automatically generated by MyBatis Generator, do not modify.
      This element was generated on Wed Jul 13 23:55:47 GMT+08:00 2022.
    -->
    update user
    set gmt_created = #{gmtCreated,jdbcType=TIMESTAMP},
      gmt_modified = #{gmtModified,jdbcType=TIMESTAMP},
      gmt_deleted = #{gmtDeleted,jdbcType=TIMESTAMP},
      remark = #{remark,jdbcType=VARCHAR},
      username = #{username,jdbcType=VARCHAR},
      password = #{password,jdbcType=VARCHAR},
      enabled = #{enabled,jdbcType=BIT},
      email = #{email}
    where id = #{id,jdbcType=INTEGER}
  </update>
  <select id="selectByPrimaryKey" parameterType="java.lang.Integer" resultMap="BaseResultMap">
    <!--
      WARNING - @mbg.generated
      This element is automatically generated by MyBatis Generator, do not modify.
      This element was generated on Wed Jul 13 23:55:47 GMT+08:00 2022.
    -->
    select id, gmt_created, gmt_modified, gmt_deleted, remark, username, password, enabled, email
    from user
    where id = #{id,jdbcType=INTEGER}
  </select>
  <select id="selectAll" resultMap="BaseResultMap">
    <!--
      WARNING - @mbg.generated
      This element is automatically generated by MyBatis Generator, do not modify.
      This element was generated on Wed Jul 13 23:55:47 GMT+08:00 2022.
    -->
    select id, gmt_created, gmt_modified, gmt_deleted, remark, username, password, enabled, email
    from user
  </select>

  <select id="selectUsernameAndPasswordByUsername" resultMap="BaseResultMap" parameterType="string">
    select username, password
    from user
    where username = #{username}
  </select>
    <select id="selectUserByEmail" resultType="cn.ch1tanda.event.model.User">
    select id, gmt_created, gmt_modified, gmt_deleted, remark, username, password, enabled, email
    from user
    where email=#{email} and gmt_deleted is null;
    </select>
</mapper>